{"uid":"xnnqhh1775kvmz2r","name":"Blood Brothers","faction":"Battle Brothers","units":[{"id":"c_fG6LZ9W","name":"Blood Master Destroyer","size":1,"cost":135,"quality":3,"defense":3,"rules":["Ambush","Hero","Tough","Fearless","Bloodborn"],"weapons":[{"id":"h4Ntaf0B","name":"CCW","type":"ArmyBookWeapon","count":1,"range":0,"attacks":4,"weaponId":"KAsYqgPq","specialRules":[],"attacksMultiplier":1,"label":"CCW (A4)","originalCount":1}],"upgrades":["PzePx","gIdERs5O"]},{"id":"7Y8nYEx_O","name":"Blood Veteran Master Brother","size":1,"cost":60,"quality":3,"defense":3,"rules":["Hero","Tough","Fearless","Versatile Attack","Bloodborn"],"weapons":[{"id":"LSkqpzPG","name":"CCW","type":"ArmyBookWeapon","count":1,"range":0,"attacks":2,"weaponId":"83nhlNHF","specialRules":[],"attacksMultiplier":1,"label":"CCW (A2)","originalCount":1}],"upgrades":["B1","HkK5EImr","9gPjzFMb"]},{"id":"j1x9MKxDU","name":"Blood Master Brother","size":1,"cost":55,"quality":3,"defense":3,"rules":["Hero","Tough","Fearless","Bloodborn"],"weapons":[{"id":"lXOrCYv-","name":"Flamer Pistol","type":"ArmyBookWeapon","count":1,"range":6,"attacks":1,"weaponId":"agIlKQ_g","specialRules":[{"type":"ArmyBookRule","id":"w_vX0mi58KKt","name":"Blast","rating":3,"label":"Blast(3)"},{"type":"ArmyBookRule","id":"Zx4mWN0SbmK8","name":"Reliable","label":"Reliable"}],"attacksMultiplier":1,"label":"Flamer Pistol (6\", A1, Blast(3), Reliable)","originalCount":1},{"id":"LSkqpzPG","name":"CCW","type":"ArmyBookWeapon","count":1,"range":0,"attacks":2,"weaponId":"83nhlNHF","specialRules":[],"attacksMultiplier":1,"label":"CCW (A2)","originalCount":1}],"upgrades":["A1","B1","HkK5EImr"]},{"id":"tIZg2bQx8","name":"Blood Elite Pathfinder","size":1,"cost":50,"quality":4,"defense":4,"rules":["Hero","Strider","Tough","Fearless","Bloodborn"],"weapons":[{"id":"lXOrCYv-","name":"Flamer Pistol","type":"ArmyBookWeapon","count":1,"range":6,"attacks":1,"weaponId":"agIlKQ_g","specialRules":[{"type":"ArmyBookRule","id":"w_vX0mi58KKt","name":"Blast","rating":3,"label":"Blast(3)"},{"type":"ArmyBookRule","id":"Zx4mWN0SbmK8","name":"Reliable","label":"Reliable"}],"attacksMultiplier":1,"label":"Flamer Pistol (6\", A1, Blast(3), Reliable)","originalCount":1},{"id":"LSkqpzPG","name":"CCW","type":"ArmyBookWeapon","count":1,"range":0,"attacks":2,"weaponId":"83nhlNHF","specialRules":[],"attacksMultiplier":1,"label":"CCW (A2)","originalCount":1}],"upgrades":["GPBPT","A1","O5LFWJcd"]},{"id":"3tQ59KC3Y","name":"Blood Pathfinders","size":5,"cost":115,"quality":4,"defense":4,"rules":["Strider","Fearless","Bloodborn"],"weapons":[{"id":"lXOrCYv-","name":"Heavy Pistol","type":"ArmyBookWeapon","count":5,"range":12,"attacks":1,"weaponId":"wfEHdWKY","specialRules":[{"type":"ArmyBookRule","id":"17crjK7P6_w6","name":"AP","rating":1,"label":"AP(1)"}],"attacksMultiplier":1,"label":"Heavy Pistol (12\", A1, AP(1))","originalCount":5},{"id":"LSkqpzPG","name":"CCW","type":"ArmyBookWeapon","count":5,"range":0,"attacks":2,"weaponId":"83nhlNHF","specialRules":[],"attacksMultiplier":1,"label":"CCW (A2)","originalCount":5}],"upgrades":["G1"]},{"id":"CUhMFDenY","name":"Blood Battle Brothers","size":5,"cost":150,"quality":3,"defense":3,"rules":["Fearless","Bloodborn"],"weapons":[{"id":"lXOrCYv-","name":"Heavy Rifle","type":"ArmyBookWeapon","range":24,"attacks":1,"weaponId":"lXOrCYv-","specialRules":[{"type":"ArmyBookRule","id":"17crjK7P6_w6","name":"AP","rating":1,"label":"AP(1)"}],"attacksMultiplier":1,"label":"Heavy Rifle (24\", A1, AP(1))","count":5,"originalCount":5},{"id":"LSkqpzPG","name":"CCW","type":"ArmyBookWeapon","range":0,"attacks":1,"weaponId":"4o5CBBZC","specialRules":[],"attacksMultiplier":1,"label":"CCW (A1)","count":5,"originalCount":5}],"upgrades":["D1","lBsat"]},{"id":"612zYO549","name":"Blood Assault Brothers","size":5,"cost":160,"quality":3,"defense":3,"rules":["Fearless","Bloodborn"],"weapons":[{"id":"wfEHdWKY","name":"Heavy Pistol","type":"ArmyBookWeapon","range":12,"attacks":1,"weaponId":"wfEHdWKY","specialRules":[{"type":"ArmyBookRule","id":"17crjK7P6_w6","name":"AP","rating":1,"label":"AP(1)"}],"attacksMultiplier":1,"label":"Heavy Pistol (12\", A1, AP(1))","count":5,"originalCount":5},{"id":"ln7wg3EY","name":"Heavy CCW","type":"ArmyBookWeapon","count":5,"range":0,"attacks":2,"weaponId":"BN7Zr4vd","specialRules":[{"type":"ArmyBookRule","id":"17crjK7P6_w6","name":"AP","rating":1,"label":"AP(1)"}],"attacksMultiplier":1,"label":"Heavy CCW (A2, AP(1))","originalCount":5}],"upgrades":["E1","lBsat"]},{"id":"eWFPc-osc","name":"Blood Veteran Battle Brothers","size":3,"cost":110,"quality":3,"defense":3,"rules":["Fearless","Versatile Attack","Bloodborn"],"weapons":[{"id":"lXOrCYv-","name":"Heavy Rifle","type":"ArmyBookWeapon","range":24,"attacks":1,"weaponId":"lXOrCYv-","specialRules":[{"type":"ArmyBookRule","id":"17crjK7P6_w6","name":"AP","rating":1,"label":"AP(1)"}],"attacksMultiplier":1,"label":"Heavy Rifle (24\", A1, AP(1))","count":3,"originalCount":3},{"id":"LSkqpzPG","name":"CCW","type":"ArmyBookWeapon","range":0,"attacks":1,"weaponId":"4o5CBBZC","specialRules":[],"attacksMultiplier":1,"label":"CCW (A1)","count":3,"originalCount":3}],"upgrades":["C_pZc","lBsat"]},{"id":"lOKoAbID1","name":"Blood Veteran Assault Brothers","size":3,"cost":85,"quality":3,"defense":3,"rules":["Fearless","Versatile Attack","Bloodborn"],"weapons":[{"id":"iAJsotA9","name":"Heavy Pistol","type":"ArmyBookWeapon","count":3,"range":12,"attacks":1,"weaponId":"wfEHdWKY","specialRules":[{"type":"ArmyBookRule","id":"17crjK7P6_w6","name":"AP","rating":1,"label":"AP(1)"}],"attacksMultiplier":1,"label":"Heavy Pistol (12\", A1, AP(1))","originalCount":3}],"upgrades":["GEMr7","lBsat"]},{"id":"mzbsOyv","name":"Blood Death Brothers","size":5,"cost":160,"quality":3,"defense":3,"rules":["Regeneration","Bloodborn","Fearless"],"weapons":[{"id":"-4KV4","name":"Heavy Rifle","type":"ArmyBookWeapon","count":5,"range":24,"attacks":1,"weaponId":"lXOrCYv-","specialRules":[{"type":"ArmyBookRule","id":"17crjK7P6_w6","name":"AP","rating":1,"label":"AP(1)"}],"attacksMultiplier":1,"label":"Heavy Rifle (24\", A1, AP(1))","originalCount":5},{"id":"Ovp1m","name":"CCW","type":"ArmyBookWeapon","count":5,"range":0,"attacks":1,"weaponId":"4o5CBBZC","specialRules":[],"attacksMultiplier":1,"label":"CCW (A1)","originalCount":5}],"upgrades":["mx7zJ","bNs23_vM"]},{"id":"exMSgVu","name":"Blood Guard Brothers","size":5,"cost":210,"quality":3,"defense":3,"rules":["Ambush","Flying","Bloodborn","Fearless"],"weapons":[{"id":"R2AWx","name":"Assault Pistol","type":"ArmyBookWeapon","range":12,"attacks":2,"weaponId":"a3QKSRN3","specialRules":[],"attacksMultiplier":1,"label":"Assault Pistol (12\", A2)","count":5,"originalCount":5},{"id":"lxWi4","name":"Heavy CCW","type":"ArmyBookWeapon","count":5,"range":0,"attacks":2,"weaponId":"BN7Zr4vd","specialRules":[{"type":"ArmyBookRule","id":"17crjK7P6_w6","name":"AP","rating":1,"label":"AP(1)"}],"attacksMultiplier":1,"label":"Heavy CCW (A2, AP(1))","originalCount":5}],"upgrades":["WdFlV","lBsat"]},{"id":"e7j6yiCmq","name":"Blood Support Brothers","size":3,"cost":130,"quality":3,"defense":3,"rules":["Relentless","Fearless","Bloodborn"],"weapons":[{"id":"9KbQ3D9t","name":"Heavy Flamer","type":"ArmyBookWeapon","count":3,"range":12,"attacks":1,"weaponId":"9KbQ3D9t","specialRules":[{"type":"ArmyBookRule","id":"17crjK7P6_w6","name":"AP","rating":1,"label":"AP(1)"},{"type":"ArmyBookRule","id":"w_vX0mi58KKt","name":"Blast","rating":3,"label":"Blast(3)"},{"type":"ArmyBookRule","id":"Zx4mWN0SbmK8","name":"Reliable","label":"Reliable"}],"attacksMultiplier":1,"label":"Heavy Flamer (12\", A1, AP(1), Blast(3), Reliable)","originalCount":3},{"id":"LSkqpzPG","name":"CCW","type":"ArmyBookWeapon","range":0,"attacks":1,"weaponId":"4o5CBBZC","specialRules":[],"attacksMultiplier":1,"label":"CCW (A1)","count":3,"originalCount":3}],"upgrades":["F1"]},{"id":"HIJQq11yt","name":"Blood Destroyers","size":3,"cost":210,"quality":3,"defense":3,"rules":["Ambush","Tough","Fearless","Bloodborn"],"weapons":[{"id":"BrMvKziy","name":"CCW","type":"ArmyBookWeapon","count":3,"range":0,"attacks":3,"weaponId":"tO5jEqMO","specialRules":[],"attacksMultiplier":1,"label":"CCW (A3)","originalCount":3}],"upgrades":["H1","lBsat"]},{"id":"iwwW_S6kH","name":"Blood Pathfinder Bikers","size":3,"cost":210,"quality":4,"defense":4,"rules":["Tough","Fearless","Bloodborn"],"weapons":[{"id":"C9Hnetww","name":"Grenade Launcher","type":"ArmyBookWeapon","range":24,"attacks":1,"weaponId":"C9Hnetww","specialRules":[{"type":"ArmyBookRule","id":"w_vX0mi58KKt","name":"Blast","rating":3,"label":"Blast(3)"}],"attacksMultiplier":1,"label":"Grenade Launcher (24\", A1, Blast(3))","count":3,"originalCount":3},{"id":"wfEHdWKY","name":"Heavy Pistol","type":"ArmyBookWeapon","range":12,"attacks":1,"weaponId":"wfEHdWKY","specialRules":[{"type":"ArmyBookRule","id":"17crjK7P6_w6","name":"AP","rating":1,"label":"AP(1)"}],"attacksMultiplier":1,"label":"Heavy Pistol (12\", A1, AP(1))","count":3,"originalCount":3},{"id":"ln7wg3EY","name":"CCW","type":"ArmyBookWeapon","range":0,"attacks":2,"weaponId":"83nhlNHF","specialRules":[],"attacksMultiplier":1,"label":"CCW (A2)","count":3,"originalCount":3}],"upgrades":["I1"]},{"id":"fzy49s6h7","name":"Blood Brother Bikers","size":3,"cost":280,"quality":3,"defense":3,"rules":["Fast","Tough","Fearless","Bloodborn"],"weapons":[{"id":"wbSELVAM","name":"Twin Heavy Rifle","type":"ArmyBookWeapon","range":24,"attacks":2,"weaponId":"wbSELVAM","specialRules":[{"type":"ArmyBookRule","id":"17crjK7P6_w6","name":"AP","rating":1,"label":"AP(1)"}],"attacksMultiplier":1,"label":"Twin Heavy Rifle (24\", A2, AP(1))","count":3,"originalCount":3},{"id":"wfEHdWKY","name":"Heavy Pistol","type":"ArmyBookWeapon","range":12,"attacks":1,"weaponId":"wfEHdWKY","specialRules":[{"type":"ArmyBookRule","id":"17crjK7P6_w6","name":"AP","rating":1,"label":"AP(1)"}],"attacksMultiplier":1,"label":"Heavy Pistol (12\", A1, AP(1))","count":3,"originalCount":3},{"id":"ln7wg3EY","name":"CCW","type":"ArmyBookWeapon","range":0,"attacks":2,"weaponId":"83nhlNHF","specialRules":[],"attacksMultiplier":1,"label":"CCW (A2)","count":3,"originalCount":3}],"upgrades":["J1"]},{"id":"olfSoqrsx","name":"Blood Support Bike","size":1,"cost":175,"quality":3,"defense":3,"rules":["Fast","Tough","Fearless","Bloodborn"],"weapons":[{"id":"wbSELVAM","name":"Twin Heavy Rifle","type":"ArmyBookWeapon","range":24,"attacks":2,"weaponId":"wbSELVAM","specialRules":[{"type":"ArmyBookRule","id":"17crjK7P6_w6","name":"AP","rating":1,"label":"AP(1)"}],"attacksMultiplier":1,"label":"Twin Heavy Rifle (24\", A2, AP(1))","count":1,"originalCount":1},{"id":"9KbQ3D9t","name":"Heavy Flamer","type":"ArmyBookWeapon","range":12,"attacks":1,"weaponId":"9KbQ3D9t","specialRules":[{"type":"ArmyBookRule","id":"17crjK7P6_w6","name":"AP","rating":1,"label":"AP(1)"},{"type":"ArmyBookRule","id":"w_vX0mi58KKt","name":"Blast","rating":3,"label":"Blast(3)"},{"type":"ArmyBookRule","id":"Zx4mWN0SbmK8","name":"Reliable","label":"Reliable"}],"attacksMultiplier":1,"label":"Heavy Flamer (12\", A1, AP(1), Blast(3), Reliable)","count":1,"originalCount":1},{"id":"wfEHdWKY","name":"Heavy Pistol","type":"ArmyBookWeapon","range":12,"attacks":1,"weaponId":"wfEHdWKY","specialRules":[{"type":"ArmyBookRule","id":"17crjK7P6_w6","name":"AP","rating":1,"label":"AP(1)"}],"attacksMultiplier":1,"label":"Heavy Pistol (12\", A1, AP(1))","count":1,"originalCount":1},{"id":"jnrN7AN5","name":"CCW","type":"ArmyBookWeapon","range":0,"attacks":3,"weaponId":"tO5jEqMO","specialRules":[],"attacksMultiplier":1,"label":"CCW (A3)","count":1,"originalCount":1}],"upgrades":["K1","SXDm_AqS"]},{"id":"w3IgD6IKN","name":"Blood APC","size":1,"cost":210,"quality":3,"defense":2,"rules":["Fast","Impact","Tough","Transport","Fearless","Bloodborn"],"weapons":[{"id":"tFsK8C2w","name":"Storm Rifle","type":"ArmyBookWeapon","range":24,"attacks":3,"weaponId":"tFsK8C2w","specialRules":[{"type":"ArmyBookRule","id":"17crjK7P6_w6","name":"AP","rating":1,"label":"AP(1)"}],"attacksMultiplier":1,"label":"Storm Rifle (24\", A3, AP(1))","count":1,"originalCount":1}],"upgrades":["A2"]},{"id":"2cfW5f4Zc","name":"Blood Attack APC","size":1,"cost":205,"quality":3,"defense":2,"rules":["Fast","Impact","Tough","Transport","Fearless","Bloodborn"],"weapons":[{"id":"4ORrcD9V","name":"Twin Heavy Flamer","type":"ArmyBookWeapon","range":12,"attacks":2,"weaponId":"4ORrcD9V","specialRules":[{"type":"ArmyBookRule","id":"17crjK7P6_w6","name":"AP","rating":1,"label":"AP(1)"},{"type":"ArmyBookRule","id":"w_vX0mi58KKt","name":"Blast","rating":3,"label":"Blast(3)"},{"type":"ArmyBookRule","id":"Zx4mWN0SbmK8","name":"Reliable","label":"Reliable"}],"attacksMultiplier":1,"label":"Twin Heavy Flamer (12\", A2, AP(1), Blast(3), Reliable)","count":1,"originalCount":1}],"upgrades":["B2"]},{"id":"0L0Xv94OD","name":"Blood Drop Pod","size":1,"cost":150,"quality":3,"defense":2,"rules":["Ambush","Immobile","Tough","Transport","Fearless","Bloodborn"],"weapons":[{"id":"5a62gwmA","name":"Death Launcher","type":"ArmyBookWeapon","range":18,"attacks":1,"weaponId":"5a62gwmA","specialRules":[{"type":"ArmyBookRule","id":"w_vX0mi58KKt","name":"Blast","rating":6,"label":"Blast(6)"}],"attacksMultiplier":1,"label":"Death Launcher (18\", A1, Blast(6))","count":1,"originalCount":1}],"upgrades":["C2","SXDm_AqS"]},{"id":"fi0XsuNMr","name":"Blood Battle Tank","size":1,"cost":475,"quality":3,"defense":2,"rules":["Fast","Tough","Impact","Fearless","Bloodborn"],"weapons":[{"id":"rKG95U4w","name":"Twin Heavy Machinegun","type":"ArmyBookWeapon","range":30,"attacks":6,"weaponId":"rKG95U4w","specialRules":[{"type":"ArmyBookRule","id":"17crjK7P6_w6","name":"AP","rating":1,"label":"AP(1)"}],"attacksMultiplier":1,"label":"Twin Heavy Machinegun (30\", A6, AP(1))","count":1,"originalCount":1},{"id":"igysAgIf","name":"Twin Storm Cannon","type":"ArmyBookWeapon","count":1,"range":30,"attacks":4,"weaponId":"rjkVZjTQ","specialRules":[{"type":"ArmyBookRule","id":"17crjK7P6_w6","name":"AP","rating":2,"label":"AP(2)"},{"type":"ArmyBookRule","id":"QXyt-zV_bjpg","name":"Unstoppable","label":"Unstoppable"}],"attacksMultiplier":1,"label":"Twin Storm Cannon (30\", A4, AP(2), Unstoppable)","originalCount":1}],"upgrades":["A2","D2"]},{"id":"jteDOBPuV","name":"Blood Heavy Tank","size":1,"cost":750,"quality":3,"defense":2,"rules":["Fast","Tough","Impact","Transport","Fearless","Bloodborn"],"weapons":[{"id":"rKG95U4w","name":"Twin Heavy Machinegun","type":"ArmyBookWeapon","range":30,"attacks":6,"weaponId":"rKG95U4w","specialRules":[{"type":"ArmyBookRule","id":"17crjK7P6_w6","name":"AP","rating":1,"label":"AP(1)"}],"attacksMultiplier":1,"label":"Twin Heavy Machinegun (30\", A6, AP(1))","count":1,"originalCount":1},{"id":"c8ItDl9q","name":"Quad Flamer Cannon","type":"ArmyBookWeapon","count":1,"range":18,"attacks":4,"weaponId":"1T1V1Qym","specialRules":[{"type":"ArmyBookRule","id":"17crjK7P6_w6","name":"AP","rating":1,"label":"AP(1)"},{"type":"ArmyBookRule","id":"w_vX0mi58KKt","name":"Blast","rating":3,"label":"Blast(3)"},{"type":"ArmyBookRule","id":"Zx4mWN0SbmK8","name":"Reliable","label":"Reliable"}],"attacksMultiplier":1,"label":"Quad Flamer Cannon (18\", A4, AP(1), Blast(3), Reliable)","originalCount":1}],"upgrades":["E2","A2"]},{"id":"Lmzb2YOtc","name":"Blood Artillery Gun","size":1,"cost":175,"quality":3,"defense":3,"rules":["Artillery","Fearless","Tough","Bloodborn"],"weapons":[{"id":"Zi1AU9Md","name":"Heavy Gatling Cannon","type":"ArmyBookWeapon","count":1,"range":24,"attacks":6,"weaponId":"eybBFIky","specialRules":[{"type":"ArmyBookRule","id":"17crjK7P6_w6","name":"AP","rating":1,"label":"AP(1)"}],"attacksMultiplier":1,"label":"Heavy Gatling Cannon (24\", A6, AP(1))","originalCount":1},{"id":"bdeiiP6m","name":"Crew","type":"ArmyBookWeapon","count":1,"range":0,"attacks":3,"weaponId":"RVHL9W8F","specialRules":[],"attacksMultiplier":1,"label":"Crew (A3)","originalCount":1}],"upgrades":["F2"]},{"id":"aGUzve4Qs","name":"Blood Attack Speeder","size":1,"cost":225,"quality":3,"defense":2,"rules":["Ambush","Fast","Impact","Strider","Tough","Fearless","Bloodborn"],"weapons":[{"id":"9KbQ3D9t","name":"Heavy Flamer","type":"ArmyBookWeapon","count":2,"range":12,"attacks":1,"weaponId":"9KbQ3D9t","specialRules":[{"type":"ArmyBookRule","id":"17crjK7P6_w6","name":"AP","rating":1,"label":"AP(1)"},{"type":"ArmyBookRule","id":"w_vX0mi58KKt","name":"Blast","rating":3,"label":"Blast(3)"},{"type":"ArmyBookRule","id":"Zx4mWN0SbmK8","name":"Reliable","label":"Reliable"}],"attacksMultiplier":1,"label":"2x Heavy Flamer (12\", A1, AP(1), Blast(3), Reliable)","originalCount":2}],"upgrades":["G2"]},{"id":"Mm3O9u9bm","name":"Blood Heavy Exo-Suit","size":1,"cost":160,"quality":3,"defense":2,"rules":["Fear","Tough","Fearless","Bloodborn"],"weapons":[{"id":"_Hj4DhLu","name":"Twin Flamer","type":"ArmyBookWeapon","count":1,"range":12,"attacks":2,"weaponId":"zxi2iITn","specialRules":[{"type":"ArmyBookRule","id":"w_vX0mi58KKt","name":"Blast","rating":3,"label":"Blast(3)"},{"type":"ArmyBookRule","id":"Zx4mWN0SbmK8","name":"Reliable","label":"Reliable"}],"attacksMultiplier":1,"label":"Twin Flamer (12\", A2, Blast(3), Reliable)","originalCount":1},{"id":"Gi78mcgd","name":"Stomp","type":"ArmyBookWeapon","range":0,"attacks":2,"weaponId":"hyB0WaAL","specialRules":[{"type":"ArmyBookRule","id":"17crjK7P6_w6","name":"AP","rating":1,"label":"AP(1)"}],"attacksMultiplier":1,"label":"Stomp (A2, AP(1))","count":1,"originalCount":1}],"upgrades":["H2"]},{"id":"vmdb3SZH1","name":"Blood Combat Walker","size":1,"cost":365,"quality":3,"defense":2,"rules":["Fear","Tough","Fearless","Bloodborn"],"weapons":[{"id":"zbPgLa2-","name":"Stomp","type":"ArmyBookWeapon","range":0,"attacks":4,"weaponId":"l9ncuAr5","specialRules":[{"type":"ArmyBookRule","id":"17crjK7P6_w6","name":"AP","rating":1,"label":"AP(1)"}],"attacksMultiplier":1,"label":"Stomp (A4, AP(1))","count":1,"originalCount":1},{"id":"YGzB6","name":"Walker Fist","type":"ArmyBookWeapon","count":2,"range":0,"attacks":4,"weaponId":"S50qDyJ5","specialRules":[{"type":"ArmyBookRule","id":"17crjK7P6_w6","name":"AP","rating":4,"label":"AP(4)"}],"attacksMultiplier":1,"label":"2x Walker Fist (A4, AP(4))","originalCount":2}],"upgrades":["I2","tgyb1"]},{"id":"OeF1zNCx_","name":"Blood Veteran Combat Walker","size":1,"cost":400,"quality":3,"defense":2,"rules":["Fear","Tough","Fearless","Versatile Attack","Bloodborn"],"weapons":[{"id":"zbPgLa2-","name":"Stomp","type":"ArmyBookWeapon","range":0,"attacks":4,"weaponId":"l9ncuAr5","specialRules":[{"type":"ArmyBookRule","id":"17crjK7P6_w6","name":"AP","rating":1,"label":"AP(1)"}],"attacksMultiplier":1,"label":"Stomp (A4, AP(1))","count":1,"originalCount":1},{"id":"gHbKx","name":"Walker Fist","type":"ArmyBookWeapon","count":2,"range":0,"attacks":4,"weaponId":"S50qDyJ5","specialRules":[{"type":"ArmyBookRule","id":"17crjK7P6_w6","name":"AP","rating":4,"label":"AP(4)"}],"attacksMultiplier":1,"label":"2x Walker Fist (A4, AP(4))","originalCount":2}],"upgrades":["I2","tgyb1"]},{"id":"X53mSnaoe","name":"Blood Light Gunship","size":1,"cost":310,"quality":3,"defense":2,"rules":["Aircraft","Tough","Fearless","Bloodborn"],"weapons":[{"id":"uzLqUcvY","name":"Minigun","type":"ArmyBookWeapon","range":24,"attacks":4,"weaponId":"uzLqUcvY","specialRules":[{"type":"ArmyBookRule","id":"17crjK7P6_w6","name":"AP","rating":1,"label":"AP(1)"}],"attacksMultiplier":1,"label":"Minigun (24\", A4, AP(1))","count":1,"originalCount":1},{"id":"82BqH4A9","name":"Twin Typhoon Missiles","type":"ArmyBookWeapon","range":24,"attacks":4,"weaponId":"82BqH4A9","specialRules":[{"type":"ArmyBookRule","id":"17crjK7P6_w6","name":"AP","rating":2,"label":"AP(2)"},{"type":"ArmyBookRule","id":"QXyt-zV_bjpg","name":"Unstoppable","label":"Unstoppable"}],"attacksMultiplier":1,"label":"Twin Typhoon Missiles (24\", A4, AP(2), Unstoppable)","count":1,"originalCount":1}],"upgrades":["J2"]},{"id":"AnP6jCXNu","name":"Blood Heavy Gunship","size":1,"cost":625,"quality":3,"defense":2,"rules":["Aircraft","Tough","Transport","Fearless","Bloodborn"],"weapons":[{"id":"hDsUEk_6","name":"Storm Missiles","type":"ArmyBookWeapon","range":36,"attacks":1,"weaponId":"hDsUEk_6","specialRules":[{"type":"ArmyBookRule","id":"17crjK7P6_w6","name":"AP","rating":3,"label":"AP(3)"},{"type":"ArmyBookRule","id":"_mrPya5SXSqW","name":"Deadly","rating":3,"label":"Deadly(3)"}],"attacksMultiplier":1,"label":"Storm Missiles (36\", A1, AP(3), Deadly(3))","count":1,"originalCount":1},{"id":"tUQ-t","name":"Light Heavy Rifle Array","type":"ArmyBookWeapon","count":1,"range":24,"attacks":4,"weaponId":"46B-13fX","specialRules":[{"type":"ArmyBookRule","id":"17crjK7P6_w6","name":"AP","rating":1,"label":"AP(1)"}],"attacksMultiplier":1,"label":"Light Heavy Rifle Array (24\", A4, AP(1))","originalCount":1},{"id":"jmiQjniq","name":"Twin Minigun","type":"ArmyBookWeapon","range":24,"attacks":8,"weaponId":"jmiQjniq","specialRules":[{"type":"ArmyBookRule","id":"17crjK7P6_w6","name":"AP","rating":1,"label":"AP(1)"}],"attacksMultiplier":1,"label":"Twin Minigun (24\", A8, AP(1))","count":1,"originalCount":1},{"id":"Iw7wN8NG","name":"Typhoon Missiles","type":"ArmyBookWeapon","range":24,"attacks":2,"weaponId":"Iw7wN8NG","specialRules":[{"type":"ArmyBookRule","id":"17crjK7P6_w6","name":"AP","rating":2,"label":"AP(2)"},{"type":"ArmyBookRule","id":"QXyt-zV_bjpg","name":"Unstoppable","label":"Unstoppable"}],"attacksMultiplier":1,"label":"Typhoon Missiles (24\", A2, AP(2), Unstoppable)","count":1,"originalCount":1}],"upgrades":["K2"]}]}