{"uid":"z8205ez2boggzs22","name":"DAO Union","faction":"","units":[{"id":"ZLsGVby","name":"Battle Suit Elite","size":1,"cost":155,"quality":4,"defense":3,"rules":["Flying","Hero","Tough","Targeting Visor"],"weapons":[{"id":"A0EYz","name":"Suit-Burst","type":"ArmyBookWeapon","count":2,"range":18,"attacks":1,"weaponId":"RUWQuEpU","specialRules":[{"type":"ArmyBookRule","id":"cavWDboL4ubs","name":"Rending","label":"Rending"}],"attacksMultiplier":1,"label":"2x Suit-Burst (18\", A1, Rending)","originalCount":2},{"id":"UwVdr3ko","name":"Suit-Flamer","type":"ArmyBookWeapon","count":2,"range":12,"attacks":1,"weaponId":"UkbXjF_m","specialRules":[{"type":"ArmyBookRule","id":"w_vX0mi58KKt","name":"Blast","rating":3,"label":"Blast(3)"},{"type":"ArmyBookRule","id":"Zx4mWN0SbmK8","name":"Reliable","label":"Reliable"}],"attacksMultiplier":1,"label":"2x Suit-Flamer (12\", A1, Blast(3), Reliable)","originalCount":2},{"id":"QnrnAIok","name":"Bash","type":"ArmyBookWeapon","range":null,"attacks":4,"weaponId":"QnrnAIok","specialRules":[{"type":"ArmyBookRule","id":"17crjK7P6_w6","name":"AP","rating":1,"label":"AP(1)"}],"attacksMultiplier":1,"label":"Bash (A4, AP(1))","count":1,"originalCount":1}],"upgrades":["B1","UA0trVt1","PPFyeuLW"]},{"id":"wbcHuwv","name":"Grunt Leader","size":1,"cost":25,"quality":5,"defense":4,"rules":["Good Shot","Hero","Targeting Visor","Tough"],"weapons":[{"id":"0906Ch_R","name":"Holy Baton","type":"ArmyBookWeapon","count":1,"range":0,"attacks":1,"weaponId":"55BYSuPp","specialRules":[{"type":"ArmyBookRule","id":"w_vX0mi58KKt","name":"Blast","rating":3,"label":"Blast(3)"}],"attacksMultiplier":1,"label":"Holy Baton (A1, Blast(3))","originalCount":1}],"upgrades":["B1","C1","WRmsr"]},{"id":"KRznAPH","name":"Security Grunts","size":5,"cost":105,"quality":5,"defense":4,"rules":["Good Shot","Targeting Visor"],"weapons":[{"id":"0906Ch_R","name":"Pulse Shotgun","type":"ArmyBookWeapon","range":12,"attacks":2,"weaponId":"0906Ch_R","specialRules":[{"type":"ArmyBookRule","id":"17crjK7P6_w6","name":"AP","rating":1,"label":"AP(1)"}],"attacksMultiplier":1,"label":"Pulse Shotgun (12\", A2, AP(1))","count":5,"originalCount":5},{"id":"sXxOWV9q","name":"CCW","type":"ArmyBookWeapon","range":0,"attacks":1,"weaponId":"4o5CBBZC","specialRules":[],"attacksMultiplier":1,"label":"CCW (A1)","count":5,"originalCount":5}],"upgrades":["83qdO-bm","oCGcS1ry"]},{"id":"l9y9wn9","name":"Tactical Grunts","size":5,"cost":115,"quality":5,"defense":4,"rules":["Good Shot","Targeting Visor"],"weapons":[{"id":"0906Ch_R","name":"Pulse Rifle","type":"ArmyBookWeapon","count":5,"range":30,"attacks":1,"weaponId":"veVXGB-j","specialRules":[{"type":"ArmyBookRule","id":"17crjK7P6_w6","name":"AP","rating":1,"label":"AP(1)"}],"attacksMultiplier":1,"label":"Pulse Rifle (30\", A1, AP(1))","originalCount":5},{"id":"sXxOWV9q","name":"CCW","type":"ArmyBookWeapon","range":0,"attacks":1,"weaponId":"4o5CBBZC","specialRules":[],"attacksMultiplier":1,"label":"CCW (A1)","count":5,"originalCount":5}],"upgrades":["F1","G1"]},{"id":"fdAp19o","name":"Spotter Squad","size":5,"cost":145,"quality":5,"defense":5,"rules":["Good Shot","Scout","Targeting Visor"],"weapons":[{"id":"TsHJJMv4","name":"Pulse Carbine","type":"ArmyBookWeapon","range":18,"attacks":2,"weaponId":"TsHJJMv4","specialRules":[{"type":"ArmyBookRule","id":"17crjK7P6_w6","name":"AP","rating":1,"label":"AP(1)"}],"attacksMultiplier":1,"label":"Pulse Carbine (18\", A2, AP(1))","count":5,"originalCount":5},{"id":"sXxOWV9q","name":"CCW","type":"ArmyBookWeapon","range":0,"attacks":1,"weaponId":"4o5CBBZC","specialRules":[],"attacksMultiplier":1,"label":"CCW (A1)","count":5,"originalCount":5}],"upgrades":["H1"]},{"id":"_Xaptlm","name":"Stealth Suits","size":3,"cost":250,"quality":4,"defense":4,"rules":["Ambush","Stealth","Targeting Visor","Tough"],"weapons":[{"id":"P-ssikDQ","name":"Rapid Burst Carbine","type":"ArmyBookWeapon","count":3,"range":18,"attacks":4,"weaponId":"Yr6bDzeO","specialRules":[{"type":"ArmyBookRule","id":"cavWDboL4ubs","name":"Rending","label":"Rending"}],"attacksMultiplier":1,"label":"Rapid Burst Carbine (18\", A4, Rending)","originalCount":3},{"id":"sXxOWV9q","name":"CCW","type":"ArmyBookWeapon","range":0,"attacks":1,"weaponId":"4o5CBBZC","specialRules":[],"attacksMultiplier":1,"label":"CCW (A1)","count":3,"originalCount":3}],"upgrades":["I1"]},{"id":"ky_P-X8","name":"Battle Suits","size":3,"cost":220,"quality":4,"defense":3,"rules":["Flying","Tough","Targeting Visor"],"weapons":[{"id":"Fk6FFDc1","name":"Suit-Burst","type":"ArmyBookWeapon","count":9,"range":18,"attacks":1,"weaponId":"RUWQuEpU","specialRules":[{"type":"ArmyBookRule","id":"cavWDboL4ubs","name":"Rending","label":"Rending"}],"attacksMultiplier":1,"label":"3x Suit-Burst (18\", A1, Rending)","originalCount":9},{"id":"CccO_p00","name":"Bash","type":"ArmyBookWeapon","range":0,"attacks":2,"weaponId":"m-NC5mq1","specialRules":[],"attacksMultiplier":1,"label":"Bash (A2)","count":3,"originalCount":3}],"upgrades":["F1","Oa7j1nk0","J1"]},{"id":"pBa-dzK","name":"Gun Drones","size":5,"cost":150,"quality":5,"defense":4,"rules":["Targeting Visor","Good Shot","Strider"],"weapons":[{"id":"XdpN39lq","name":"Twin Pulse-Gun","type":"ArmyBookWeapon","range":18,"attacks":2,"weaponId":"XdpN39lq","specialRules":[{"type":"ArmyBookRule","id":"cavWDboL4ubs","name":"Rending","label":"Rending"}],"attacksMultiplier":1,"label":"Twin Pulse-Gun (18\", A2, Rending)","count":5,"originalCount":5},{"id":"cu3dkWTG","name":"Taser","type":"ArmyBookWeapon","range":null,"attacks":1,"weaponId":"cu3dkWTG","specialRules":[],"attacksMultiplier":1,"label":"Taser (A1)","count":5,"originalCount":5}],"upgrades":["K1"]},{"id":"7zBLXHS","name":"Sniper Drones","size":3,"cost":75,"quality":5,"defense":4,"rules":["Good Shot","Strider","Targeting Visor"],"weapons":[{"id":"veVXGB-j","name":"Pulse Rifle","type":"ArmyBookWeapon","range":30,"attacks":1,"weaponId":"veVXGB-j","specialRules":[{"type":"ArmyBookRule","id":"17crjK7P6_w6","name":"AP","rating":1,"label":"AP(1)"}],"attacksMultiplier":1,"label":"Pulse Rifle (30\", A1, AP(1))","count":3,"originalCount":3},{"id":"cu3dkWTG","name":"Taser","type":"ArmyBookWeapon","range":null,"attacks":1,"weaponId":"cu3dkWTG","specialRules":[],"attacksMultiplier":1,"label":"Taser (A1)","count":3,"originalCount":3}],"upgrades":["L1"]},{"id":"AjN0k6Z","name":"Hover Transport","size":1,"cost":220,"quality":4,"defense":2,"rules":["Fast","Impact","Strider","Targeting Visor","Tough","Transport"],"weapons":[{"id":"41BTn29X","name":"Heavy Burst Carbine","type":"ArmyBookWeapon","range":18,"attacks":2,"weaponId":"41BTn29X","specialRules":[{"type":"ArmyBookRule","id":"17crjK7P6_w6","name":"AP","rating":1,"label":"AP(1)"},{"type":"ArmyBookRule","id":"cavWDboL4ubs","name":"Rending","label":"Rending"}],"attacksMultiplier":1,"label":"Heavy Burst Carbine (18\", A2, AP(1), Rending)","count":1,"originalCount":1},{"id":"aZ5AxkcD","name":"Twin Heavy Pulse-Gun","type":"ArmyBookWeapon","range":18,"attacks":4,"weaponId":"aZ5AxkcD","specialRules":[{"type":"ArmyBookRule","id":"17crjK7P6_w6","name":"AP","rating":1,"label":"AP(1)"}],"attacksMultiplier":1,"label":"Twin Heavy Pulse-Gun (18\", A4, AP(1))","count":1,"originalCount":1}],"upgrades":["A2","B2","C2"]},{"id":"37mvtxH","name":"Hover Tank","size":1,"cost":370,"quality":4,"defense":2,"rules":["Fast","Impact","Strider","Targeting Visor","Tough"],"weapons":[{"id":"T_P9UIb2","name":"Sub-Railgun","type":"ArmyBookWeapon","range":36,"attacks":2,"weaponId":"T_P9UIb2","specialRules":[{"type":"ArmyBookRule","id":"17crjK7P6_w6","name":"AP","rating":1,"label":"AP(1)"},{"type":"ArmyBookRule","id":"w_vX0mi58KKt","name":"Blast","rating":3,"label":"Blast(3)"}],"attacksMultiplier":1,"label":"Sub-Railgun (36\", A2, AP(1), Blast(3))","count":1,"originalCount":1},{"id":"aZ5AxkcD","name":"Twin Heavy Pulse-Gun","type":"ArmyBookWeapon","range":18,"attacks":4,"weaponId":"aZ5AxkcD","specialRules":[{"type":"ArmyBookRule","id":"17crjK7P6_w6","name":"AP","rating":1,"label":"AP(1)"}],"attacksMultiplier":1,"label":"Twin Heavy Pulse-Gun (18\", A4, AP(1))","count":1,"originalCount":1}],"upgrades":["A2","B2","C2","D2","PUpFpK8q"]},{"id":"tY8l8ZT","name":"Hover Attack Bike","size":1,"cost":180,"quality":4,"defense":2,"rules":["Fast","Impact","Strider","Targeting Visor","Tough"],"weapons":[{"id":"P-ssikDQ","name":"Burst Carbine","type":"ArmyBookWeapon","range":18,"attacks":2,"weaponId":"P-ssikDQ","specialRules":[{"type":"ArmyBookRule","id":"cavWDboL4ubs","name":"Rending","label":"Rending"}],"attacksMultiplier":1,"label":"Burst Carbine (18\", A2, Rending)","count":1,"originalCount":1},{"id":"aZ5AxkcD","name":"Twin Heavy Pulse-Gun","type":"ArmyBookWeapon","range":18,"attacks":4,"weaponId":"aZ5AxkcD","specialRules":[{"type":"ArmyBookRule","id":"17crjK7P6_w6","name":"AP","rating":1,"label":"AP(1)"}],"attacksMultiplier":1,"label":"Twin Heavy Pulse-Gun (18\", A4, AP(1))","count":1,"originalCount":1}],"upgrades":["B2","C2","E2"]},{"id":"WtOO_AT","name":"Heavy Battle Suit","size":1,"cost":320,"quality":4,"defense":2,"rules":["Fear","Tough","Targeting Visor"],"weapons":[{"id":"FNyJ3p1i","name":"Quad Frag Pod","type":"ArmyBookWeapon","count":1,"range":24,"attacks":4,"weaponId":"FNyJ3p1i","specialRules":[{"type":"ArmyBookRule","id":"w_vX0mi58KKt","name":"Blast","rating":3,"label":"Blast(3)"},{"type":"ArmyBookRule","id":"8Ck9GAwUK824","name":"Indirect","label":"Indirect"}],"attacksMultiplier":1,"label":"Quad Frag Pod (24\", A4, Blast(3), Indirect)","originalCount":1},{"id":"gpLhmRoK","name":"Stomp","type":"ArmyBookWeapon","range":0,"attacks":4,"weaponId":"l9ncuAr5","specialRules":[{"type":"ArmyBookRule","id":"17crjK7P6_w6","name":"AP","rating":1,"label":"AP(1)"}],"attacksMultiplier":1,"label":"Stomp (A4, AP(1))","count":1,"originalCount":1}],"upgrades":["B2","F2"]},{"id":"yaCpV7v","name":"Heavy Stealth Suit","size":1,"cost":345,"quality":4,"defense":2,"rules":["Ambush","Fear","Stealth","Tough","Targeting Visor"],"weapons":[{"id":"R_o-s","name":"Heavy Ion Carbine","type":"ArmyBookWeapon","count":1,"range":18,"attacks":1,"weaponId":"Tc1jCYqN","specialRules":[{"type":"ArmyBookRule","id":"17crjK7P6_w6","name":"AP","rating":1,"label":"AP(1)"},{"type":"ArmyBookRule","id":"w_vX0mi58KKt","name":"Blast","rating":6,"label":"Blast(6)"}],"attacksMultiplier":1,"label":"Heavy Ion Carbine (18\", A1, AP(1), Blast(6))","originalCount":1},{"id":"zxi2iITn","name":"Twin Burst Carbine","type":"ArmyBookWeapon","count":1,"range":18,"attacks":4,"weaponId":"BWQAVW_z","specialRules":[{"type":"ArmyBookRule","id":"cavWDboL4ubs","name":"Rending","label":"Rending"}],"attacksMultiplier":1,"label":"Twin Burst Carbine (18\", A4, Rending)","originalCount":1},{"id":"gpLhmRoK","name":"Stomp","type":"ArmyBookWeapon","range":0,"attacks":4,"weaponId":"l9ncuAr5","specialRules":[{"type":"ArmyBookRule","id":"17crjK7P6_w6","name":"AP","rating":1,"label":"AP(1)"}],"attacksMultiplier":1,"label":"Stomp (A4, AP(1))","count":1,"originalCount":1}],"upgrades":["G2"]},{"id":"6izo3fA","name":"Razor Fighter","size":1,"cost":270,"quality":4,"defense":2,"rules":["Aircraft","Tough","Targeting Visor"],"weapons":[{"id":"OUxnSD4v","name":"Ion Cannon","type":"ArmyBookWeapon","range":30,"attacks":2,"weaponId":"OUxnSD4v","specialRules":[{"type":"ArmyBookRule","id":"17crjK7P6_w6","name":"AP","rating":2,"label":"AP(2)"},{"type":"ArmyBookRule","id":"w_vX0mi58KKt","name":"Blast","rating":3,"label":"Blast(3)"}],"attacksMultiplier":1,"label":"Ion Cannon (30\", A2, AP(2), Blast(3))","count":1,"originalCount":1},{"id":"BWQAVW_z","name":"Twin Burst Carbine","type":"ArmyBookWeapon","range":18,"attacks":4,"weaponId":"BWQAVW_z","specialRules":[{"type":"ArmyBookRule","id":"cavWDboL4ubs","name":"Rending","label":"Rending"}],"attacksMultiplier":1,"label":"Twin Burst Carbine (18\", A4, Rending)","count":1,"originalCount":1}],"upgrades":["H2","WQ5C-0dL"]},{"id":"d9Tk3DW","name":"Sun Bomber","size":1,"cost":275,"quality":4,"defense":2,"rules":["Aircraft","Tough","Targeting Visor"],"weapons":[{"id":"zuffxgRQ","name":"Ion Rifle","type":"ArmyBookWeapon","count":1,"range":30,"attacks":1,"weaponId":"zPeKQR11","specialRules":[{"type":"ArmyBookRule","id":"17crjK7P6_w6","name":"AP","rating":1,"label":"AP(1)"},{"type":"ArmyBookRule","id":"w_vX0mi58KKt","name":"Blast","rating":3,"label":"Blast(3)"}],"attacksMultiplier":1,"label":"Ion Rifle (30\", A1, AP(1), Blast(3))","originalCount":1},{"id":"3Mzbhiko","name":"Missile Pod","type":"ArmyBookWeapon","count":1,"range":30,"attacks":2,"weaponId":"HYG4v4Rx","specialRules":[{"type":"ArmyBookRule","id":"1qiGNqpxKb24","name":"Disintegrate","label":"Disintegrate"},{"type":"ArmyBookRule","id":"QXyt-zV_bjpg","name":"Unstoppable","label":"Unstoppable"}],"attacksMultiplier":1,"label":"Missile Pod (30\", A2, Disintegrate, Unstoppable)","originalCount":1},{"id":"v1VTN_Yu","name":"Pulse Bombs","type":"ArmyBookWeapon","range":0,"attacks":2,"weaponId":"v1VTN_Yu","specialRules":[{"type":"ArmyBookRule","id":"17crjK7P6_w6","name":"AP","rating":1,"label":"AP(1)"},{"type":"ArmyBookRule","id":"w_vX0mi58KKt","name":"Blast","rating":3,"label":"Blast(3)"},{"type":"ArmyBookRule","id":"Hdm9ry6kJvzb","name":"Strafing","label":"Strafing"}],"attacksMultiplier":1,"label":"Pulse Bombs (A2, AP(1), Blast(3), Strafing)","count":1,"originalCount":1}],"upgrades":["WQ5C-0dL"]},{"id":"JdvBC-d","name":"Tide Titan","size":1,"cost":505,"quality":4,"defense":2,"rules":["Fear","Tough","Targeting Visor"],"weapons":[{"id":"0B4V90Ve","name":"Twin Plasma Rifle","type":"ArmyBookWeapon","range":24,"attacks":2,"weaponId":"0B4V90Ve","specialRules":[{"type":"ArmyBookRule","id":"17crjK7P6_w6","name":"AP","rating":4,"label":"AP(4)"}],"attacksMultiplier":1,"label":"Twin Plasma Rifle (24\", A2, AP(4))","count":1,"originalCount":1},{"id":"w_Ye4T6p","name":"Heavy Plasma Sword","type":"ArmyBookWeapon","count":2,"range":0,"attacks":8,"weaponId":"w_Ye4T6p","specialRules":[{"type":"ArmyBookRule","id":"17crjK7P6_w6","name":"AP","rating":1,"label":"AP(1)"},{"type":"ArmyBookRule","id":"cavWDboL4ubs","name":"Rending","label":"Rending"}],"attacksMultiplier":1,"label":"2x Heavy Plasma Sword (A8, AP(1), Rending)","originalCount":2},{"id":"4aOyLySX","name":"Stomp","type":"ArmyBookWeapon","range":0,"attacks":6,"weaponId":"BvXlHjOH","specialRules":[{"type":"ArmyBookRule","id":"17crjK7P6_w6","name":"AP","rating":2,"label":"AP(2)"}],"attacksMultiplier":1,"label":"Stomp (A6, AP(2))","count":1,"originalCount":1}],"upgrades":["J2"]},{"id":"1B1nvAM","name":"Surge Titan","size":1,"cost":710,"quality":4,"defense":2,"rules":["Fear","Tough","Targeting Visor"],"weapons":[{"id":"FnoPH7CZ","name":"Cluster Rockets","type":"ArmyBookWeapon","range":24,"attacks":8,"weaponId":"FnoPH7CZ","specialRules":[{"type":"ArmyBookRule","id":"17crjK7P6_w6","name":"AP","rating":1,"label":"AP(1)"}],"attacksMultiplier":1,"label":"Cluster Rockets (24\", A8, AP(1))","count":1,"originalCount":1},{"id":"JWXpwLtp","name":"Pulse Blaster","type":"ArmyBookWeapon","range":24,"attacks":3,"weaponId":"JWXpwLtp","specialRules":[{"type":"ArmyBookRule","id":"17crjK7P6_w6","name":"AP","rating":2,"label":"AP(2)"},{"type":"ArmyBookRule","id":"w_vX0mi58KKt","name":"Blast","rating":3,"label":"Blast(3)"}],"attacksMultiplier":1,"label":"Pulse Blaster (24\", A3, AP(2), Blast(3))","count":1,"originalCount":1},{"id":"0WRwwuLO","name":"Stomp","type":"ArmyBookWeapon","range":0,"attacks":8,"weaponId":"OjIL2pMY","specialRules":[{"type":"ArmyBookRule","id":"17crjK7P6_w6","name":"AP","rating":2,"label":"AP(2)"}],"attacksMultiplier":1,"label":"Stomp (A8, AP(2))","count":1,"originalCount":1}],"upgrades":["K2"]}]}